README.rst
setup.py
triangle.py
triangle_plot.egg-info/PKG-INFO
triangle_plot.egg-info/SOURCES.txt
triangle_plot.egg-info/dependency_links.txt
triangle_plot.egg-info/top_level.txt