Metadata-Version: 1.1
Name: triangle-plot
Version: 0.3.0
Summary: Make some beautiful corner plots of samples.
Home-page: https://github.com/dfm/triangle.py
Author: Daniel Foreman-Mackey
Author-email: danfm@nyu.edu
License: UNKNOWN
Platform: UNKNOWN
Classifier: Development Status :: 5 - Production/Stable
Classifier: License :: OSI Approved :: BSD License
Classifier: Intended Audience :: Developers
Classifier: Intended Audience :: Science/Research
Classifier: Operating System :: OS Independent
Classifier: Programming Language :: Python
